# 3.5 Python性能剖析与优化GIL常考题

- GIL:Global Interpreter Lock
	- CPython解释器的内存管理并不是线程安全的，多线程如果同时修改一个对象可能导致问题
	- 保护多线程情况下对Python对象的访问
	- CPython使用简单的锁机制避免多个线程同时执行字节码
- GIL的影响<font color="red">**限制了线程的多核执行**</font>
	- 同一时间只能有一个线程执行字节码
	- CPU密集程序难以利用多核优势
	- IO期间会释放GIL，对IO密集程序影响不大
- 如何规避GIL影响： <font color="red">**区分CPU和IO密集程序**</font>
	- CPU密集可以使用多进程+进程池
	- IO密集使用多线程/协程
	- cpython扩展
- GIL实现
	- 每隔一段时间释放当前的锁，让其它线程去获取锁
- 练习  
	```python
	import threading
	
	n = [0]
	
	def foo():
	    n[0] = n[0] + 1
	    n[0] = n[0] + 1
	
	threads = []
	for i in range(5000):
	    t = threading.Thread(target=foo)
	    threads.append(t)
	for t in threads:
	    t.start()
	print(n)
	```
	- 执行结果不定
- 为什么有了GIL还要关注线程安全
	- Python中什么操作才是原子的？一步到位执行完
		- 一个操作如果是一个字节码指定可以完成就是原子的
		- 原子的是可以保证线程安全的
		- 使用dis操作来分析字节码 
	- 原子操作是线程安全的
	```python
	import dis
	
	def update_list(l):
	    l[0] = 1  # 原子操作，不用担心线程安全问题
	
	print(dis.dis(update_list))
	"""
	  5           0 LOAD_CONST               1 (1)
	              2 LOAD_FAST                0 (l)
	              4 LOAD_CONST               2 (0)
	              6 STORE_SUBSCR             # 单字节码操作，线程安全
	              8 LOAD_CONST               0 (None)
	             10 RETURN_VALUE
	"""
	``` 
	- 非原子操作不是线程安全的
	```python
	import dis
	
	def incr_list(l):
	    l[0] += 1  # 危险！！不是原子操作
	
	print(dis.dis(incr_list))
	"""
	  5           0 LOAD_FAST                0 (l)
	              2 LOAD_CONST               1 (0)
	              4 DUP_TOP_TWO
	              6 BINARY_SUBSCR
	              8 LOAD_CONST               2 (1)
	             10 INPLACE_ADD              # 需要多个字节码操作
	             12 ROT_THREE                # 有可能在线程执行过程中切换到其它线程
	             14 STORE_SUBSCR
	             16 LOAD_CONST               0 (None)
	             18 RETURN_VALUE
	"""
	```
- 如何保证线程安全
	- 加锁
	```python
	import threading
	
	lock = threading.Lock()
	
	n = [0]
	
	def foo():
	    with lock:
	        n[0] = n[0] + 1
	        n[0] = n[0] + 1
	
	threads = []
	for i in range(5000):
	    t = threading.Thread(target=foo)
	    threads.append(t)
	
	for t in threads:
	    t.start()
	
	print(n)
	```
- 如何剖析程序性能
	- 使用各种profile工具（内置或第三方）
		- 二八定律，大部分时间消耗在少量代码上
		- 内置的profile/cprofile等工具
		- 使用pyflame（uber开源）的火焰图工具
- 服务端性能优化措施
	- Web应用一般语言不会成为瓶颈
		- 数据结构与算法优化
		- 数据库层：索引优化、慢查询消除，批量操作减少多次IO，引入NoSQL提高性能
		- 网络IO：批量操作，pipeline操作减少IO请求次数
		- 缓存：使用内存数据库redis、memcached
		- 异步：asyncio、celery
		- 并发：gevent、多线程